lohas_app_hotel_search_gzp_mcp_server/__init__.py
lohas_app_hotel_search_gzp_mcp_server/config.py
lohas_app_hotel_search_gzp_mcp_server/hotel_intent.py
lohas_app_hotel_search_gzp_mcp_server-1.0.4.dist-info/WHEEL
lohas_app_hotel_search_gzp_mcp_server-1.0.4.dist-info/entry_points.txt
lohas_app_hotel_search_gzp_mcp_server-1.0.4.dist-info/METADATA
lohas_app_hotel_search_gzp_mcp_server-1.0.4.dist-info/RECORD
