Metadata-Version: 2.3
Name: lohas-app-hotel-search-gzp-mcp-server
Version: 1.0.4
Summary: Add your description here
Author: guzp
Author-email: guzp <857504206@qq.com>
Requires-Dist: mcp[cli]>=1.13.0
Requires-Dist: mysql-connector-python>=9.4.0
Requires-Python: >=3.10.0
